parsoc/__init__.py
parsoc/__main__.py
parsoc-0.2.0.dist-info/LICENSE.txt
parsoc-0.2.0.dist-info/METADATA
parsoc-0.2.0.dist-info/WHEEL
parsoc-0.2.0.dist-info/entry_points.txt
parsoc-0.2.0.dist-info/top_level.txt
parsoc-0.2.0.dist-info/RECORD
