Metadata-Version: 2.1
Name: parsoc
Version: 0.2.0
Summary: Convert docx files to json.
Home-page: https://github.com/fmind/parsoc
Author: Médéric Hurier (fmind)
Author-email: fmind@fmind.me
License: LGPL-3.0
Keywords: docx json parse convert
Platform: UNKNOWN
Classifier: Development Status :: 4 - Beta
Requires-Python: >=3.7
Requires-Dist: python-docx
